pygptwrapper/__init__.py
pygptwrapper/contextual.py
pygptwrapper/utils.py
pygptwrapper-0.4.0.dist-info/WHEEL
pygptwrapper-0.4.0.dist-info/METADATA
pygptwrapper-0.4.0.dist-info/RECORD
