Metadata-Version: 2.1
Name: pygptwrapper
Version: 0.4.0
Summary: Python Wrapper for the ChatGPT API
Author: Your Name
Author-email: you@example.com
Requires-Python: >=3.8,<4.0
Classifier: Programming Language :: Python :: 3
Classifier: Programming Language :: Python :: 3.8
Classifier: Programming Language :: Python :: 3.9
Classifier: Programming Language :: Python :: 3.10
Requires-Dist: openai (>=0.27.1,<0.28.0)
